{
	"isTwist": true,
	"hideInFreeplay": false,
	"difficulties": "easy, normal, hard",

	"songs": [
		{
			"songName": "Tutorial",
			"displaySongName": "Tutorial",
			"healthIcon": "gf",
			"freeplayColor": [165, 0, 77],
			"invisibleInFreeplay": false
		}
	],

	"storyMenu": {
		"title": "tutorial",
		"description": "Teaching Time",

		"characterColors": [
			"#E65580",
			"#E65580"
		],

		"bgGradientColor": [
			"#862934",
			"#57182D"
		],

		"weekCharacters": [
			"bfTutorial",
			"gfTutorial"
		],

		"weekName": "tutorial",
		"weekBackground": "stage",
		"weekBefore": "tutorial",
		"hideStoryMode": false,
		"firstTimeBlocked": false,
		"hiddenUntilUnlocked": false
	}
}